ytdriver/Video.py
ytdriver/YTDriver.py
ytdriver/__init__.py
ytdriver/example.py
ytdriver/util.py
YouTube_Driver-1.0.8.dist-info/LICENSE
YouTube_Driver-1.0.8.dist-info/METADATA
YouTube_Driver-1.0.8.dist-info/WHEEL
YouTube_Driver-1.0.8.dist-info/top_level.txt
YouTube_Driver-1.0.8.dist-info/RECORD
