Metadata-Version: 2.1
Name: YouTube-Driver
Version: 1.0.8
Summary: Programmatically interact with YouTube's interface.
Home-page: https://github.com/ucdavis-noyce/YouTube-Driver
Download-URL: https://github.com/ucdavis-noyce/YouTube-Driver/archive/refs/tags/v1.0.7.tar.gz
Author: Muhammad Haroon
Author-email: mharoon@ucdavis.edu
License: MIT
License-File: LICENSE
Requires-Dist: selenium
Requires-Dist: pyvirtualdisplay
Requires-Dist: yt-dlp
